{
  "generatedAt": "2026-07-10T12:03:48.598Z",
  "sourcePath": "C:\\Users\\NiloFranzosiFilho\\Documents\\New project\\px-outreach-engine\\.planning",
  "dashboardSourcePath": "C:\\Users\\NiloFranzosiFilho\\Documents\\New project\\px-outreach-engine\\public\\data\\thiago-abm-weekly-snapshots.json",
  "companySummary": {
    "weekKey": "2026-S28",
    "totalCompanies": 72,
    "activeCompanies": 62,
    "pausedCompanies": 10,
    "repliedOrBetterCompanies": 13,
    "meetingOrBetterCompanies": 7,
    "dealCompanies": 6,
    "companyReplyRate": 0.20967741935483872,
    "companyMeetingRate": 0.11290322580645161,
    "companyDealRate": 0.0967741935483871
  },
  "sample": {
    "activeContacts": 93,
    "replies": 13,
    "advanced": 9,
    "negatives": 1,
    "noResponse": 70,
    "replyRate": 0.13978494623655913,
    "advancedRate": 0.0967741935483871,
    "avgDaysToFirstReply": 5.769230769230769
  },
  "bySegment": [
    {
      "segment": "Farmacêutico & Saúde",
      "total": 4,
      "responded": 1,
      "advanced": 1,
      "negative": 0,
      "replyRate": 0.25,
      "advancedRate": 0.25,
      "avgDaysToFirstReply": 1
    },
    {
      "segment": "E-commerce & Varejo",
      "total": 17,
      "responded": 2,
      "advanced": 1,
      "negative": 0,
      "replyRate": 0.11764705882352941,
      "advancedRate": 0.058823529411764705,
      "avgDaysToFirstReply": 23
    },
    {
      "segment": "Cosméticos & Higiene",
      "total": 6,
      "responded": 3,
      "advanced": 2,
      "negative": 0,
      "replyRate": 0.5,
      "advancedRate": 0.3333333333333333,
      "avgDaysToFirstReply": 0.6666666666666666
    },
    {
      "segment": "Alimentos & Bebidas",
      "total": 14,
      "responded": 1,
      "advanced": 0,
      "negative": 0,
      "replyRate": 0.07142857142857142,
      "advancedRate": 0,
      "avgDaysToFirstReply": 0
    },
    {
      "segment": "Eletro & Tecnologia",
      "total": 3,
      "responded": 0,
      "advanced": 0,
      "negative": 0,
      "replyRate": 0,
      "advancedRate": 0,
      "avgDaysToFirstReply": null
    },
    {
      "segment": "Indústria Pesada",
      "total": 8,
      "responded": 1,
      "advanced": 3,
      "negative": 0,
      "replyRate": 0.125,
      "advancedRate": 0.375,
      "avgDaysToFirstReply": 7
    },
    {
      "segment": "Combustíveis, Energia & Química",
      "total": 4,
      "responded": 1,
      "advanced": 2,
      "negative": 0,
      "replyRate": 0.25,
      "advancedRate": 0.5,
      "avgDaysToFirstReply": 17
    },
    {
      "segment": "Automotivo & Pneus",
      "total": 4,
      "responded": 0,
      "advanced": 0,
      "negative": 0,
      "replyRate": 0,
      "advancedRate": 0,
      "avgDaysToFirstReply": null
    },
    {
      "segment": "Agro & Commodities",
      "total": 6,
      "responded": 0,
      "advanced": 0,
      "negative": 0,
      "replyRate": 0,
      "advancedRate": 0,
      "avgDaysToFirstReply": null
    },
    {
      "segment": "Segmento a classificar",
      "total": 26,
      "responded": 4,
      "advanced": 0,
      "negative": 1,
      "replyRate": 0.15384615384615385,
      "advancedRate": 0,
      "avgDaysToFirstReply": 0.5
    },
    {
      "segment": "Têxtil & Vestuário",
      "total": 1,
      "responded": 0,
      "advanced": 0,
      "negative": 0,
      "replyRate": 0,
      "advancedRate": 0,
      "avgDaysToFirstReply": null
    }
  ],
  "bySeniority": [
    {
      "seniority": "Não identificado",
      "total": 33,
      "responded": 5,
      "advanced": 3,
      "negative": 0,
      "replyRate": 0.15151515151515152,
      "advancedRate": 0.09090909090909091,
      "avgDaysToFirstReply": 10.8
    },
    {
      "seniority": "Diretoria / Head",
      "total": 40,
      "responded": 6,
      "advanced": 3,
      "negative": 0,
      "replyRate": 0.15,
      "advancedRate": 0.075,
      "avgDaysToFirstReply": 0.5
    },
    {
      "seniority": "Gerência / Especialista",
      "total": 10,
      "responded": 1,
      "advanced": 2,
      "negative": 0,
      "replyRate": 0.1,
      "advancedRate": 0.2,
      "avgDaysToFirstReply": 17
    },
    {
      "seniority": "C-level / VP",
      "total": 10,
      "responded": 1,
      "advanced": 1,
      "negative": 1,
      "replyRate": 0.1,
      "advancedRate": 0.1,
      "avgDaysToFirstReply": 1
    }
  ],
  "byFunctionArea": [
    {
      "functionArea": "Função a classificar",
      "total": 29,
      "responded": 3,
      "advanced": 1,
      "negative": 0,
      "replyRate": 0.10344827586206896,
      "advancedRate": 0.034482758620689655,
      "avgDaysToFirstReply": 2.6666666666666665
    },
    {
      "functionArea": "Supply / Logística / Operações",
      "total": 55,
      "responded": 10,
      "advanced": 6,
      "negative": 1,
      "replyRate": 0.18181818181818182,
      "advancedRate": 0.10909090909090909,
      "avgDaysToFirstReply": 6.7
    },
    {
      "functionArea": "Procurement / Suprimentos",
      "total": 8,
      "responded": 0,
      "advanced": 2,
      "negative": 0,
      "replyRate": 0,
      "advancedRate": 0.25,
      "avgDaysToFirstReply": null
    },
    {
      "functionArea": "Alta gestão",
      "total": 1,
      "responded": 0,
      "advanced": 0,
      "negative": 0,
      "replyRate": 0,
      "advancedRate": 0,
      "avgDaysToFirstReply": null
    }
  ],
  "byTimeBand": [
    {
      "timeBand": "Antes das 08h",
      "total": 48,
      "responded": 7,
      "advanced": 4,
      "negative": 1,
      "replyRate": 0.14583333333333334,
      "advancedRate": 0.08333333333333333,
      "avgDaysToFirstReply": 7.142857142857143
    },
    {
      "timeBand": "12h-17h59",
      "total": 19,
      "responded": 4,
      "advanced": 4,
      "negative": 0,
      "replyRate": 0.21052631578947367,
      "advancedRate": 0.21052631578947367,
      "avgDaysToFirstReply": 6.25
    },
    {
      "timeBand": "08h-11h59",
      "total": 17,
      "responded": 2,
      "advanced": 1,
      "negative": 0,
      "replyRate": 0.11764705882352941,
      "advancedRate": 0.058823529411764705,
      "avgDaysToFirstReply": 0
    },
    {
      "timeBand": "18h+",
      "total": 5,
      "responded": 0,
      "advanced": 0,
      "negative": 0,
      "replyRate": 0,
      "advancedRate": 0,
      "avgDaysToFirstReply": null
    },
    {
      "timeBand": "Sem horário",
      "total": 4,
      "responded": 0,
      "advanced": 0,
      "negative": 0,
      "replyRate": 0,
      "advancedRate": 0,
      "avgDaysToFirstReply": null
    }
  ],
  "copyStats": {
    "totalClassified": 23,
    "totalOutbound": 104,
    "byCopyVariant": [
      {
        "label": "direto",
        "total": 23,
        "responded": 6,
        "advanced": 2,
        "negative": 0,
        "replyRate": 0.2608695652173913
      }
    ],
    "byTriggerType": [
      {
        "label": "sem-gatilho",
        "total": 18,
        "responded": 6,
        "advanced": 2,
        "negative": 0,
        "replyRate": 0.3333333333333333
      },
      {
        "label": "cargo-novo",
        "total": 3,
        "responded": 0,
        "advanced": 0,
        "negative": 0,
        "replyRate": 0
      },
      {
        "label": "vaga-logistica",
        "total": 1,
        "responded": 0,
        "advanced": 0,
        "negative": 0,
        "replyRate": 0
      },
      {
        "label": "expansao",
        "total": 1,
        "responded": 0,
        "advanced": 0,
        "negative": 0,
        "replyRate": 0
      }
    ],
    "byMessageAngle": [
      {
        "label": "eficiencia",
        "total": 2,
        "responded": 2,
        "advanced": 2,
        "negative": 0,
        "replyRate": 1
      },
      {
        "label": "dor-logistica",
        "total": 15,
        "responded": 4,
        "advanced": 0,
        "negative": 0,
        "replyRate": 0.26666666666666666
      },
      {
        "label": "crescimento",
        "total": 4,
        "responded": 0,
        "advanced": 0,
        "negative": 0,
        "replyRate": 0
      },
      {
        "label": "capacidade",
        "total": 2,
        "responded": 0,
        "advanced": 0,
        "negative": 0,
        "replyRate": 0
      }
    ],
    "byProofType": [
      {
        "label": "case-cliente",
        "total": 18,
        "responded": 6,
        "advanced": 2,
        "negative": 0,
        "replyRate": 0.3333333333333333
      },
      {
        "label": "sem-prova",
        "total": 5,
        "responded": 0,
        "advanced": 0,
        "negative": 0,
        "replyRate": 0
      }
    ]
  }
}